MANIFEST.in
README.md
setup.py
project_migration/__init__.py
project_migration.egg-info/PKG-INFO
project_migration.egg-info/SOURCES.txt
project_migration.egg-info/dependency_links.txt
project_migration.egg-info/requires.txt
project_migration.egg-info/top_level.txt